YetAnotherPyOptional-0.1.1.dist-info/DESCRIPTION.rst
YetAnotherPyOptional-0.1.1.dist-info/METADATA
YetAnotherPyOptional-0.1.1.dist-info/RECORD
YetAnotherPyOptional-0.1.1.dist-info/WHEEL
YetAnotherPyOptional-0.1.1.dist-info/metadata.json
YetAnotherPyOptional-0.1.1.dist-info/top_level.txt
optional/__init__.py
optional/optional.py
