Metadata-Version: 2.0
Name: YetAnotherPyOptional
Version: 0.1.1
Summary: An optional-api for python
Home-page: https://github.com/erikthorstenson/python-optional
Author: Erik Lilljequist
Author-email: UNKNOWN
License: UNKNOWN
Keywords: Return values Declarative programming No NPE
Platform: UNKNOWN
Classifier: Development Status :: 3 - Alpha
Classifier: Intended Audience :: Developers
Classifier: Topic :: Software Development :: Build Tools
Classifier: License :: OSI Approved :: MIT License
Classifier: Programming Language :: Python :: 3.5
Classifier: Programming Language :: Python :: 3.6
